tahun_baru/__init__.py
tahun_baru/tahun_baru.py
tahun_baru-0.1.9.dist-info/METADATA
tahun_baru-0.1.9.dist-info/WHEEL
tahun_baru-0.1.9.dist-info/entry_points.txt
tahun_baru-0.1.9.dist-info/RECORD
