Metadata-Version: 2.1
Name: tahun_baru
Version: 0.1.9
Summary: Counting down new year time
License: MIT
Keywords: tahun_baru,tahun baru,tahun,aplikasi terminal,terminal,console,console app
Author: harigro
Author-email: trierbank@gmail.com
Requires-Python: >=3.10,<4.0
Classifier: Development Status :: 5 - Production/Stable
Classifier: Environment :: Console
Classifier: License :: OSI Approved :: MIT License
Classifier: Programming Language :: Python
Classifier: Programming Language :: Python :: 3
Classifier: Programming Language :: Python :: 3.10
Classifier: Programming Language :: Python :: 3.11
Classifier: Programming Language :: Python :: 3 :: Only
Requires-Dist: click (>=8.1.7,<9.0.0)
